tvkit/__init__.py
tvkit/__main__.py
tvkit/cli.py
tvkit/helpers.py
tvkit/py.typed
tvkit/quickstart.py
tvkit/api/__init__.py
tvkit/api/chart/__init__.py
tvkit/api/chart/ohlcv.py
tvkit/api/chart/utils.py
tvkit/api/chart/models/__init__.py
tvkit/api/chart/models/ohlcv.py
tvkit/api/chart/models/realtime.py
tvkit/api/chart/models/stream_models.py
tvkit/api/chart/services/__init__.py
tvkit/api/chart/services/connection_service.py
tvkit/api/chart/services/message_service.py
tvkit/api/scanner/__init__.py
tvkit/api/scanner/markets.py
tvkit/api/scanner/models/__init__.py
tvkit/api/scanner/models/scanner.py
tvkit/api/scanner/services/__init__.py
tvkit/api/scanner/services/scanner_service.py
tvkit/api/utils/__init__.py
tvkit/api/utils/indicator_service.py
tvkit/api/utils/models.py
tvkit/api/utils/symbol_validator.py
tvkit/api/utils/timestamp.py
tvkit/export/__init__.py
tvkit/export/data_exporter.py
tvkit/export/models.py
tvkit/export/formatters/__init__.py
tvkit/export/formatters/base_formatter.py
tvkit/export/formatters/csv_formatter.py
tvkit/export/formatters/json_formatter.py
tvkit/export/formatters/polars_formatter.py
tvkit-0.2.0.dist-info/licenses/LICENSE
tvkit-0.2.0.dist-info/METADATA
tvkit-0.2.0.dist-info/WHEEL
tvkit-0.2.0.dist-info/top_level.txt
tvkit-0.2.0.dist-info/RECORD
