Metadata-Version: 2.4
Name: tvkit
Version: 0.2.0
Summary: tvkit is a Python library that fetches real-time stock data from TradingView, including price, market cap, P/E ratio, ROE, and more for stocks from multiple countries. Easily access and analyze financial metrics for global markets.
Author-email: lumduan <b@candythink.com>
License-Expression: MIT
Project-URL: Homepage, https://github.com/lumduan/tvkit
Project-URL: Repository, https://github.com/lumduan/tvkit
Project-URL: Documentation, https://github.com/lumduan/tvkit#readme
Project-URL: Bug Reports, https://github.com/lumduan/tvkit/issues
Keywords: tradingview,stock,trading,finance,api,market-data
Classifier: Development Status :: 3 - Alpha
Classifier: Intended Audience :: Developers
Classifier: Programming Language :: Python :: 3
Classifier: Programming Language :: Python :: 3.11
Classifier: Programming Language :: Python :: 3.12
Classifier: Programming Language :: Python :: 3.13
Classifier: Topic :: Software Development :: Libraries :: Python Modules
Classifier: Topic :: Office/Business :: Financial
Requires-Python: >=3.11
License-File: LICENSE
Requires-Dist: pydantic>=2.0.0
Requires-Dist: websockets>=11.0.0
Requires-Dist: httpx>=0.24.0
Requires-Dist: polars>=0.19.0
Requires-Dist: pandas>=2.0.0
Requires-Dist: pyarrow>=12.0.0
Requires-Dist: matplotlib>=3.7.0
Requires-Dist: seaborn>=0.12.0
Provides-Extra: dev
Requires-Dist: ruff>=0.12.4; extra == "dev"
Requires-Dist: pytest>=8.0.0; extra == "dev"
Requires-Dist: pytest-asyncio>=0.23.0; extra == "dev"
Requires-Dist: build>=1.3.0; extra == "dev"
Requires-Dist: twine>=6.2.0; extra == "dev"
Requires-Dist: mypy>=1.17.0; extra == "dev"
Dynamic: license-file
